pyromorphite/__init__.py
pyromorphite/__version__.py
pyromorphite/bag.py
pyromorphite/dfgraph.py
pyromorphite/io.py
pyromorphite/skeleton.py
pyromorphite/utils.py
pyromorphite-0.0.3.dist-info/LICENSE
pyromorphite-0.0.3.dist-info/METADATA
pyromorphite-0.0.3.dist-info/WHEEL
pyromorphite-0.0.3.dist-info/top_level.txt
pyromorphite-0.0.3.dist-info/RECORD
