Metadata-Version: 2.1
Name: pyromorphite
Version: 0.0.3
Summary: A simple and efficient tool for process mining.
Home-page: https://pyromorphite.readthedocs.io
Author: Radu-Andrei Coanda
Author-email: radu.coanda@protonmail.com
License: BSD 3-Clause
Project-URL: Documentation, https://pyromorphite.readthedocs.io
Project-URL: Source, https://github.com/xcavation/pyromorphite
Platform: UNKNOWN
Classifier: Programming Language :: Python :: 3
Classifier: License :: OSI Approved :: BSD License
Classifier: Operating System :: OS Independent
Requires-Python: >=3.5
Requires-Dist: pandas (==0.25.3)
Requires-Dist: lxml (==4.4.2networkx==2.4.0)
